pytket/extensions/pysimplex/__init__.py
pytket/extensions/pysimplex/_metadata.py
pytket/extensions/pysimplex/py.typed
pytket/extensions/pysimplex/backends/__init__.py
pytket/extensions/pysimplex/backends/simplex_backend.py
pytket_pysimplex-0.18.0.dist-info/licenses/LICENSE
tests/test_simplex.py
pytket_pysimplex-0.18.0.dist-info/METADATA
pytket_pysimplex-0.18.0.dist-info/WHEEL
pytket_pysimplex-0.18.0.dist-info/top_level.txt
pytket_pysimplex-0.18.0.dist-info/RECORD
